{
  "timestamp": "2026-04-18T03:20:20.664385",
  "sources": {
    "blocklist.de": {
      "ipv4": 10973,
      "ipv6": 102,
      "cidr_v4": 0,
      "cidr_v6": 0,
      "total": 11075
    },
    "OpenDBL_TOR_exit_nodes": {
      "ipv4": 1328,
      "ipv6": 0,
      "cidr_v4": 0,
      "cidr_v6": 0,
      "total": 1328
    },
    "OpenDBL_BruteforceBlocker": {
      "ipv4": 372,
      "ipv6": 0,
      "cidr_v4": 0,
      "cidr_v6": 0,
      "total": 372
    },
    "OpenDBL_Block_Dshield": {
      "ipv4": 0,
      "ipv6": 0,
      "cidr_v4": 0,
      "cidr_v6": 0,
      "total": 0
    },
    "OpenDBL_SSL_Abuse_IP_list": {
      "ipv4": 0,
      "ipv6": 0,
      "cidr_v4": 0,
      "cidr_v6": 0,
      "total": 0
    },
    "OpenDBL_Talos": {
      "ipv4": 0,
      "ipv6": 0,
      "cidr_v4": 0,
      "cidr_v6": 0,
      "total": 0
    },
    "OpenDBL_IPSum_Level_3": {
      "ipv4": 15287,
      "ipv6": 0,
      "cidr_v4": 0,
      "cidr_v6": 0,
      "total": 15287
    },
    "greensnow": {
      "ipv4": 4349,
      "ipv6": 0,
      "cidr_v4": 0,
      "cidr_v6": 0,
      "total": 4349
    },
    "FireHOL": {
      "ipv4": 1,
      "ipv6": 0,
      "cidr_v4": 4384,
      "cidr_v6": 0,
      "total": 4385
    },
    "spamhaus": {
      "ipv4": 0,
      "ipv6": 0,
      "cidr_v4": 1589,
      "cidr_v6": 0,
      "total": 1589
    },
    "feodotracker": {
      "ipv4": 5,
      "ipv6": 0,
      "cidr_v4": 0,
      "cidr_v6": 0,
      "total": 5
    },
    "emergingthreats": {
      "ipv4": 5,
      "ipv6": 0,
      "cidr_v4": 1606,
      "cidr_v6": 0,
      "total": 1611
    },
    "URLhaus": 27821,
    "Phishing_Army": 154831
  },
  "total_ips": 0,
  "total_cidrs": 0,
  "total_domains": 182648,
  "errors": [
    "MalwareDomainList: HTTPSConnectionPool(host='www.malwaredomainlist.com', port=443): Max retries exceeded with url: /hostslist/hosts.txt (Caused by ConnectTimeoutError(<HTTPSConnection(host='www.malwaredomainlist.com', port=443) at 0x7f10e95b0250>, 'Connection to www.malwaredomainlist.com timed out. (connect timeout=30)'))"
  ],
  "total_ipv4": 28890,
  "total_ipv6": 102,
  "total_cidr_v4": 4591,
  "total_cidr_v6": 0,
  "combined_total": 216231
}