{
  "timestamp": "2026-03-15T03:21:33.371246",
  "sources": {
    "blocklist.de": {
      "ipv4": 30558,
      "ipv6": 152,
      "cidr_v4": 0,
      "cidr_v6": 0,
      "total": 30710
    },
    "OpenDBL_TOR_exit_nodes": {
      "ipv4": 1187,
      "ipv6": 0,
      "cidr_v4": 0,
      "cidr_v6": 0,
      "total": 1187
    },
    "OpenDBL_BruteforceBlocker": {
      "ipv4": 670,
      "ipv6": 0,
      "cidr_v4": 0,
      "cidr_v6": 0,
      "total": 670
    },
    "OpenDBL_Block_Dshield": {
      "ipv4": 0,
      "ipv6": 0,
      "cidr_v4": 0,
      "cidr_v6": 0,
      "total": 0
    },
    "OpenDBL_SSL_Abuse_IP_list": {
      "ipv4": 0,
      "ipv6": 0,
      "cidr_v4": 0,
      "cidr_v6": 0,
      "total": 0
    },
    "OpenDBL_Talos": {
      "ipv4": 0,
      "ipv6": 0,
      "cidr_v4": 0,
      "cidr_v6": 0,
      "total": 0
    },
    "OpenDBL_IPSum_Level_3": {
      "ipv4": 19385,
      "ipv6": 0,
      "cidr_v4": 0,
      "cidr_v6": 0,
      "total": 19385
    },
    "greensnow": {
      "ipv4": 4824,
      "ipv6": 0,
      "cidr_v4": 0,
      "cidr_v6": 0,
      "total": 4824
    },
    "FireHOL": {
      "ipv4": 1,
      "ipv6": 0,
      "cidr_v4": 4567,
      "cidr_v6": 0,
      "total": 4568
    },
    "spamhaus": {
      "ipv4": 0,
      "ipv6": 0,
      "cidr_v4": 1532,
      "cidr_v6": 0,
      "total": 1532
    },
    "feodotracker": {
      "ipv4": 5,
      "ipv6": 0,
      "cidr_v4": 0,
      "cidr_v6": 0,
      "total": 5
    },
    "emergingthreats": {
      "ipv4": 5,
      "ipv6": 0,
      "cidr_v4": 1549,
      "cidr_v6": 0,
      "total": 1554
    },
    "URLhaus": 25228,
    "Phishing_Army": 154387
  },
  "total_ips": 0,
  "total_cidrs": 0,
  "total_domains": 179611,
  "errors": [
    "MalwareDomainList: HTTPSConnectionPool(host='www.malwaredomainlist.com', port=443): Max retries exceeded with url: /hostslist/hosts.txt (Caused by ConnectTimeoutError(<HTTPSConnection(host='www.malwaredomainlist.com', port=443) at 0x7f454f423390>, 'Connection to www.malwaredomainlist.com timed out. (connect timeout=30)'))"
  ],
  "total_ipv4": 43947,
  "total_ipv6": 152,
  "total_cidr_v4": 4695,
  "total_cidr_v6": 0,
  "combined_total": 228405
}